{
    "article": [
        {
            "sort": "talking javascript php works galgame",
            "essaypic_path": "test",
            "headline": "test",
            "essay_path": "test",
            "briefIntro": "test",
            "time": "test"
        }
    ],
    "personal": {
        "name": "test",
        "headpic_path": "test",
        "tag": [
            "test",
            "test",
            "test"
        ],
        "contact_Way": {
            "QQ": "test",
            "blibli": "test",
            "mail": "test"
        }
    },
    "logindata":{
        "result":null,
        "status":null,
        "script":null,
        "left":0
    }
}